skyline_apiserver/__init__.py
skyline_apiserver/__main__.py
skyline_apiserver/context.py
skyline_apiserver/main.py
skyline_apiserver/py.typed
skyline_apiserver/version.py
skyline_apiserver/api/__init__.py
skyline_apiserver/api/deps.py
skyline_apiserver/api/v1/__init__.py
skyline_apiserver/api/v1/contrib.py
skyline_apiserver/api/v1/extension.py
skyline_apiserver/api/v1/login.py
skyline_apiserver/api/v1/policy.py
skyline_apiserver/api/v1/prometheus.py
skyline_apiserver/api/v1/setting.py
skyline_apiserver/api/wrapper/__init__.py
skyline_apiserver/api/wrapper/openstack.py
skyline_apiserver/api/wrapper/skyline.py
skyline_apiserver/client/__init__.py
skyline_apiserver/client/utils.py
skyline_apiserver/client/openstack/__init__.py
skyline_apiserver/client/openstack/cinder.py
skyline_apiserver/client/openstack/glance.py
skyline_apiserver/client/openstack/keystone.py
skyline_apiserver/client/openstack/neutron.py
skyline_apiserver/client/openstack/nova.py
skyline_apiserver/client/openstack/system.py
skyline_apiserver/cmd/__init__.py
skyline_apiserver/cmd/generate_nginx.py
skyline_apiserver/cmd/generate_sample_config.py
skyline_apiserver/cmd/generate_swagger.py
skyline_apiserver/cmd/policy_manager.py
skyline_apiserver/config/__init__.py
skyline_apiserver/config/base.py
skyline_apiserver/config/default.py
skyline_apiserver/config/openstack.py
skyline_apiserver/config/setting.py
skyline_apiserver/core/__init__.py
skyline_apiserver/core/security.py
skyline_apiserver/db/__init__.py
skyline_apiserver/db/api.py
skyline_apiserver/db/base.py
skyline_apiserver/db/models.py
skyline_apiserver/db/alembic/README
skyline_apiserver/db/alembic/__init__.py
skyline_apiserver/db/alembic/alembic.ini
skyline_apiserver/db/alembic/env.py
skyline_apiserver/db/alembic/script.py.mako
skyline_apiserver/db/alembic/versions/000_init.py
skyline_apiserver/db/alembic/versions/__init__.py
skyline_apiserver/log/__init__.py
skyline_apiserver/policy/__init__.py
skyline_apiserver/policy/base.py
skyline_apiserver-7.0.0.dist-info/AUTHORS
skyline_apiserver-7.0.0.dist-info/LICENSE
skyline_apiserver-7.0.0.dist-info/METADATA
skyline_apiserver-7.0.0.dist-info/WHEEL
skyline_apiserver-7.0.0.dist-info/entry_points.txt
skyline_apiserver-7.0.0.dist-info/pbr.json
skyline_apiserver-7.0.0.dist-info/top_level.txt
skyline_apiserver-7.0.0.dist-info/RECORD
