Metadata-Version: 2.1
Name: skyline-apiserver
Version: 7.0.0
Summary: OpenStack Skyline APIServer
Home-page: https://docs.openstack.org/skyline-apiserver/latest/
Author: OpenStack
Author-email: openstack-discuss@lists.openstack.org
Project-URL: Source, https://opendev.org/openstack/skyline-apiserver
Project-URL: Tracker, https://bugs.launchpad.net/skyline-apiserver
Classifier: Environment :: OpenStack
Classifier: Intended Audience :: Information Technology
Classifier: Intended Audience :: System Administrators
Classifier: License :: OSI Approved :: Apache Software License
Classifier: Operating System :: POSIX :: Linux
Classifier: Programming Language :: Python
Classifier: Programming Language :: Python :: Implementation :: CPython
Classifier: Programming Language :: Python :: 3 :: Only
Classifier: Programming Language :: Python :: 3
Classifier: Programming Language :: Python :: 3.8
Classifier: Programming Language :: Python :: 3.9
Classifier: Programming Language :: Python :: 3.10
Classifier: Programming Language :: Python :: 3.11
Requires-Python: >=3.8
License-File: LICENSE
License-File: AUTHORS
Requires-Dist: pbr >=5.8.0
Requires-Dist: fastapi >=0.111.0
Requires-Dist: pydantic <3.0.0,>=2.11.7
Requires-Dist: uvicorn ==0.30.1
Requires-Dist: gunicorn >=20.1.0
Requires-Dist: python-jose <=3.3.0
Requires-Dist: databases >=0.9.0
Requires-Dist: aiomysql >=0.2.0
Requires-Dist: aiosqlite >=0.20.0
Requires-Dist: loguru <=0.5.3
Requires-Dist: PyYAML >=5.4.1
Requires-Dist: immutables >=0.16
Requires-Dist: alembic >=1.7.5
Requires-Dist: httpx >=0.16.1
Requires-Dist: SQLAlchemy >=1.3.24
Requires-Dist: PyMySQL >=0.9.3
Requires-Dist: dnspython >=2.1.0
Requires-Dist: click >=7.1.2
Requires-Dist: jinja2 >=2.11.3
Requires-Dist: h11 >=0.11
Requires-Dist: MarkupSafe >=2.0.1
Requires-Dist: python-multipart >=0.0.5
Requires-Dist: python-keystoneclient >=3.21.0
Requires-Dist: python-cinderclient >=8.1.0
Requires-Dist: python-glanceclient >=2.17.1
Requires-Dist: python-neutronclient >=6.14.1
Requires-Dist: python-novaclient >=15.1.1
Requires-Dist: keystoneauth1 >=3.17.4
Requires-Dist: oslo.policy >=2.3.4
Requires-Dist: types-six >=1.16.0
